dmprj/__init__.py
dmprj/base/__init__.py
dmprj/base/messages.py
dmprj/concept/__init__.py
dmprj/concept/behavioral/__init__.py
dmprj/concept/behavioral/base.py
dmprj/concept/behavioral/context.py
dmprj/concept/behavioral/provider.py
dmprj/concept/behavioral/revision.py
dmprj/concept/structural/__init__.py
dmprj/concept/structural/container.py
dmprj/concept/structural/entity.py
dmprj/concept/structural/node.py
dmprj/concept/structural/versioned.py
dmprj/engineering/__init__.py
dmprj/engineering/boot/__init__.py
dmprj/engineering/boot/loader.py
dmprj/engineering/chore/__init__.py
dmprj/engineering/chore/dispatch.py
dmprj/engineering/chore/job.py
dmprj/engineering/chore/task.py
dmprj/engineering/hpcluster/__init__.py
dmprj/engineering/hpcluster/partition.py
dmprj/engineering/hpcluster/scheduler.py
dmprj/engineering/remote/__init__.py
dmprj/engineering/remote/rsh.py
dmprj/engineering/remote/ssh.py
dmprj/engineering/remote/telnet.py
dmprj/engineering/schema/__init__.py
dmprj/engineering/schema/base.py
dmprj/engineering/schema/bief.py
dmprj/engineering/versioncontrol/__init__.py
dmprj/engineering/versioncontrol/actions.py
dmprj/engineering/versioncontrol/actuators.py
dmprj/engineering/versioncontrol/base.py
dmprj/engineering/versioncontrol/providers.py
dmprj/engineering/versioncontrol/scope.py
dmprj-0.23011.2602016.dist-info/METADATA
dmprj-0.23011.2602016.dist-info/WHEEL
dmprj-0.23011.2602016.dist-info/top_level.txt
dmprj-0.23011.2602016.dist-info/RECORD
