Metadata-Version: 2.1
Name: dmprj
Version: 0.23011.2602016
Summary: Dedicated Modeling Project
Author-email: Xingeng  Chen <cxg@studio.home>
License: Apache License
Project-URL: Homepage, http://rcs.studio.home/project/dmp
Keywords: Modeling
Classifier: Development Status :: 4 - Beta
Classifier: Intended Audience :: Developers
Classifier: License :: OSI Approved :: Apache Software License
Classifier: Operating System :: OS Independent
Classifier: Programming Language :: Python
Classifier: Programming Language :: Python :: 3
Classifier: Programming Language :: Python :: 3 :: Only
Classifier: Topic :: Software Development :: Libraries :: Python Modules
Requires-Python: >=3.8
